{"type":"FeatureCollection","features":[{"type":"Feature","id":1031212,"geometry":{"type":"Polygon","coordinates":[[[-85.035,44.178],[-85.042,44.182],[-85.072,44.19],[-85.073,44.19],[-85.075,44.178],[-85.064,44.171],[-85.041,44.166],[-85.035,44.178]]]},"properties":{"OBJECTID":1031212,"CUSTOMER_COUNT":29,"CREW_ASSIGNED":0,"GROUP_LEVEL":0,"SHAPE.STArea()":5146106.1130719939,"SHAPE.STLength()":9272.9913401234844,"JOB_ID":"69366db195eafa47fc5f3b75","NEEDS_UPDATED":0,"EST_TIME_RESTORATION":1765189800000,"CAUSE_CD":"5fa41397b71bb212402bcdf7","CAUSE_DESC":"Other","OUTAGE_TIME":1765174701000,"EST_TIME_ETR":1765174706000,"DisplayStormMessaging":0}}]}