{"type":"FeatureCollection","features":[{"type":"Feature","id":716610,"geometry":{"type":"Polygon","coordinates":[[[-84.223,42.83],[-84.228,42.855],[-84.241,42.859],[-84.267,42.865],[-84.269,42.864],[-84.277,42.862],[-84.278,42.844],[-84.277,42.842],[-84.255,42.827],[-84.237,42.828],[-84.226,42.828],[-84.223,42.83]]]},"properties":{"OBJECTID":716610,"CUSTOMER_COUNT":209,"CREW_ASSIGNED":1,"GROUP_LEVEL":2,"SHAPE.STArea()":14156016.95730922,"SHAPE.STLength()":14500.844020851313,"JOB_ID":"65e7cefb72ce4428200ee4b7","NEEDS_UPDATED":0,"EST_TIME_RESTORATION":1709735400000,"CAUSE_CD":"5fa41397b71bb212402bcdeb","CAUSE_DESC":"Trees","OUTAGE_TIME":1709690572000}},{"type":"Feature","id":716626,"geometry":{"type":"Polygon","coordinates":[[[-85.53,42.628],[-85.529,42.629],[-85.53,42.63],[-85.544,42.644],[-85.545,42.643],[-85.56,42.63],[-85.541,42.622],[-85.54,42.622],[-85.538,42.622],[-85.538,42.622],[-85.53,42.628]]]},"properties":{"OBJECTID":716626,"CUSTOMER_COUNT":311,"CREW_ASSIGNED":1,"GROUP_LEVEL":2,"SHAPE.STArea()":3220475.3003608459,"SHAPE.STLength()":7140.345908641084,"JOB_ID":"65e816f572ce4428200f4df9","NEEDS_UPDATED":0,"EST_TIME_RESTORATION":1709731800000,"CAUSE_CD":"5fa41397b71bb212402bcdec","CAUSE_DESC":"Trees","OUTAGE_TIME":1709698365000}}]}