{"type":"FeatureCollection","features":[{"type":"Feature","id":1004091,"geometry":{"type":"Polygon","coordinates":[[[-84.26,42.586],[-84.273,42.597],[-84.299,42.596],[-84.312,42.585],[-84.299,42.574],[-84.278,42.576],[-84.273,42.577],[-84.26,42.586]]]},"properties":{"OBJECTID":1004091,"JOB_ID":"68cc59f795eafa4668c5b84c","CUSTOMER_COUNT":72,"CREW_ASSIGNED":1,"GROUP_LEVEL":1,"NEEDS_UPDATED":0,"EST_TIME_RESTORATION":1758240000000,"CAUSE_CD":null,"CAUSE_DESC":null,"OUTAGE_TIME":1758222703000,"HEADQUARTER":"LAN","SHAPE.STArea()":7447585.3982996494,"SHAPE.STLength()":10591.484230788674}},{"type":"Feature","id":1004095,"geometry":{"type":"Polygon","coordinates":[[[-84.418,44.015],[-84.418,44.017],[-84.447,44.019],[-84.454,44.017],[-84.453,44.016],[-84.446,44.009],[-84.438,44.007],[-84.427,44.009],[-84.418,44.015]]]},"properties":{"OBJECTID":1004095,"JOB_ID":"68cc5dff95eafa4668c5c3f0","CUSTOMER_COUNT":37,"CREW_ASSIGNED":1,"GROUP_LEVEL":0,"NEEDS_UPDATED":0,"EST_TIME_RESTORATION":1758240900000,"CAUSE_CD":null,"CAUSE_DESC":null,"OUTAGE_TIME":1758223661000,"HEADQUARTER":"CLR","SHAPE.STArea()":2557524.3000191008,"SHAPE.STLength()":6801.0524752647179}},{"type":"Feature","id":1004104,"geometry":{"type":"Polygon","coordinates":[[[-84.677,44.355],[-84.678,44.359],[-84.689,44.397],[-84.69,44.397],[-84.703,44.405],[-84.734,44.421],[-84.745,44.419],[-84.809,44.407],[-84.809,44.405],[-84.809,44.405],[-84.8,44.364],[-84.682,44.345],[-84.682,44.345],[-84.681,44.345],[-84.681,44.345],[-84.679,44.347],[-84.678,44.348],[-84.677,44.355]]]},"properties":{"OBJECTID":1004104,"JOB_ID":"68cc630795eafa4668c5ca22","CUSTOMER_COUNT":2143,"CREW_ASSIGNED":0,"GROUP_LEVEL":3,"NEEDS_UPDATED":0,"EST_TIME_RESTORATION":1758245400000,"CAUSE_CD":"5fa41397b71bb212402bcdec","CAUSE_DESC":"Trees","OUTAGE_TIME":1758225144000,"HEADQUARTER":"WBR","SHAPE.STArea()":61850881.476936541,"SHAPE.STLength()":31127.029779060846}},{"type":"Feature","id":1004111,"geometry":{"type":"Polygon","coordinates":[[[-84.671,44.371],[-84.684,44.373],[-84.694,44.373],[-84.696,44.372],[-84.696,44.372],[-84.684,44.351],[-84.678,44.351],[-84.677,44.351],[-84.671,44.371]]]},"properties":{"OBJECTID":1004111,"JOB_ID":"68cc658995eafa4668c5fa1d","CUSTOMER_COUNT":241,"CREW_ASSIGNED":0,"GROUP_LEVEL":2,"NEEDS_UPDATED":0,"EST_TIME_RESTORATION":1758248100000,"CAUSE_CD":null,"CAUSE_DESC":null,"OUTAGE_TIME":1758225160000,"HEADQUARTER":"WBR","SHAPE.STArea()":3057272.3666212335,"SHAPE.STLength()":7293.7383480271492}},{"type":"Feature","id":1004113,"geometry":{"type":"Polygon","coordinates":[[[-84.868,42.102],[-84.875,42.103],[-84.885,42.102],[-84.886,42.101],[-84.898,42.08],[-84.892,42.072],[-84.868,42.102]]]},"properties":{"OBJECTID":1004113,"JOB_ID":"68cc65d395eafa4668c5ffaa","CUSTOMER_COUNT":48,"CREW_ASSIGNED":1,"GROUP_LEVEL":0,"NEEDS_UPDATED":0,"EST_TIME_RESTORATION":1758242700000,"CAUSE_CD":null,"CAUSE_DESC":null,"OUTAGE_TIME":1758225873000,"HEADQUARTER":"CLD","SHAPE.STArea()":3378655.5748847439,"SHAPE.STLength()":8877.9728265817339}},{"type":"Feature","id":1004125,"geometry":{"type":"Polygon","coordinates":[[[-84.309,43.524],[-84.31,43.529],[-84.331,43.533],[-84.358,43.526],[-84.356,43.524],[-84.31,43.513],[-84.31,43.52],[-84.309,43.524]]]},"properties":{"OBJECTID":1004125,"JOB_ID":"68cc6e5495eafa4668c62837","CUSTOMER_COUNT":51,"CREW_ASSIGNED":0,"GROUP_LEVEL":1,"NEEDS_UPDATED":0,"EST_TIME_RESTORATION":1758252600000,"CAUSE_CD":null,"CAUSE_DESC":null,"OUTAGE_TIME":1758227939000,"HEADQUARTER":"MDL","SHAPE.STArea()":5062597.0288259005,"SHAPE.STLength()":10109.052416245833}},{"type":"Feature","id":1004128,"geometry":{"type":"Polygon","coordinates":[[[-84.013,43.495],[-84.013,43.504],[-84.014,43.508],[-84.014,43.508],[-84.029,43.495],[-84.029,43.494],[-84.027,43.492],[-84.014,43.481],[-84.014,43.482],[-84.013,43.495]]]},"properties":{"OBJECTID":1004128,"JOB_ID":"68cc703f95eafa4668c62c75","CUSTOMER_COUNT":73,"CREW_ASSIGNED":1,"GROUP_LEVEL":1,"NEEDS_UPDATED":0,"EST_TIME_RESTORATION":1758248100000,"CAUSE_CD":null,"CAUSE_DESC":null,"OUTAGE_TIME":1758228365000,"HEADQUARTER":"SAG","SHAPE.STArea()":2077611.8101105809,"SHAPE.STLength()":6923.9819918421535}},{"type":"Feature","id":1004152,"geometry":{"type":"Polygon","coordinates":[[[-84.682,43.757],[-84.687,43.767],[-84.688,43.767],[-84.748,43.762],[-84.763,43.759],[-84.762,43.757],[-84.748,43.748],[-84.707,43.746],[-84.687,43.75],[-84.682,43.757]]]},"properties":{"OBJECTID":1004152,"JOB_ID":"68cc80be95eafa4668c67265","CUSTOMER_COUNT":82,"CREW_ASSIGNED":0,"GROUP_LEVEL":1,"NEEDS_UPDATED":0,"EST_TIME_RESTORATION":null,"CAUSE_CD":null,"CAUSE_DESC":null,"OUTAGE_TIME":1758232763000,"HEADQUARTER":"CLR","SHAPE.STArea()":10722122.917663669,"SHAPE.STLength()":14982.572072554705}},{"type":"Feature","id":1004003,"geometry":{"type":"Polygon","coordinates":[[[-85.176,44.943],[-85.176,44.944],[-85.18,44.947],[-85.182,44.946],[-85.183,44.941],[-85.183,44.938],[-85.177,44.942],[-85.176,44.943]]]},"properties":{"OBJECTID":1004003,"JOB_ID":"68cc182672ce440b981a05c0","CUSTOMER_COUNT":35,"CREW_ASSIGNED":1,"GROUP_LEVEL":0,"NEEDS_UPDATED":0,"EST_TIME_RESTORATION":1758249900000,"CAUSE_CD":null,"CAUSE_DESC":null,"OUTAGE_TIME":1758205789000,"HEADQUARTER":"TRA","SHAPE.STArea()":299561.28345419391,"SHAPE.STLength()":2383.5144651062737}},{"type":"Feature","id":1004033,"geometry":{"type":"Polygon","coordinates":[[[-84.77,41.769],[-84.77,41.769],[-84.77,41.769],[-84.77,41.769],[-84.77,41.769],[-84.769,41.769],[-84.769,41.769],[-84.769,41.769],[-84.769,41.77],[-84.769,41.77],[-84.769,41.77],[-84.769,41.77],[-84.769,41.77],[-84.769,41.771],[-84.769,41.771],[-84.769,41.771],[-84.769,41.771],[-84.769,41.771],[-84.769,41.771],[-84.77,41.771],[-84.77,41.771],[-84.77,41.772],[-84.77,41.772],[-84.77,41.772],[-84.77,41.772],[-84.77,41.772],[-84.771,41.772],[-84.771,41.772],[-84.771,41.772],[-84.771,41.772],[-84.772,41.772],[-84.772,41.772],[-84.772,41.772],[-84.772,41.772],[-84.772,41.772],[-84.773,41.772],[-84.773,41.772],[-84.773,41.772],[-84.773,41.772],[-84.773,41.771],[-84.773,41.771],[-84.773,41.771],[-84.773,41.771],[-84.773,41.77],[-84.773,41.77],[-84.773,41.77],[-84.773,41.77],[-84.772,41.77],[-84.772,41.77],[-84.772,41.77],[-84.772,41.77],[-84.772,41.769],[-84.772,41.769],[-84.771,41.769],[-84.771,41.769],[-84.771,41.769],[-84.771,41.769],[-84.77,41.769]]]},"properties":{"OBJECTID":1004033,"JOB_ID":"68cc247572ce440b981a3a47","CUSTOMER_COUNT":2,"CREW_ASSIGNED":1,"GROUP_LEVEL":0,"NEEDS_UPDATED":0,"EST_TIME_RESTORATION":1758238200000,"CAUSE_CD":null,"CAUSE_DESC":null,"OUTAGE_TIME":1758208948000,"HEADQUARTER":"CLD","SHAPE.STArea()":107216.81123876254,"SHAPE.STLength()":1203.2438015274058}},{"type":"Feature","id":1004039,"geometry":{"type":"Polygon","coordinates":[[[-83.951,44.211],[-83.951,44.211],[-83.95,44.211],[-83.95,44.211],[-83.95,44.211],[-83.95,44.212],[-83.949,44.212],[-83.949,44.212],[-83.949,44.212],[-83.949,44.212],[-83.949,44.213],[-83.949,44.213],[-83.949,44.213],[-83.949,44.213],[-83.95,44.214],[-83.95,44.214],[-83.95,44.214],[-83.951,44.214],[-83.951,44.214],[-83.952,44.214],[-83.952,44.214],[-83.952,44.214],[-83.953,44.213],[-83.953,44.213],[-83.953,44.213],[-83.953,44.213],[-83.953,44.213],[-83.953,44.212],[-83.953,44.212],[-83.953,44.212],[-83.953,44.212],[-83.953,44.212],[-83.953,44.212],[-83.952,44.211],[-83.952,44.211],[-83.952,44.211],[-83.952,44.211],[-83.951,44.211]]]},"properties":{"OBJECTID":1004039,"JOB_ID":"68cc2d6372ce440b981a6c95","CUSTOMER_COUNT":2,"CREW_ASSIGNED":1,"GROUP_LEVEL":0,"NEEDS_UPDATED":0,"EST_TIME_RESTORATION":1758249000000,"CAUSE_CD":null,"CAUSE_DESC":null,"OUTAGE_TIME":1758210825000,"HEADQUARTER":"WBR","SHAPE.STArea()":80276.716592056677,"SHAPE.STLength()":1007.8439105689363}},{"type":"Feature","id":1004043,"geometry":{"type":"Polygon","coordinates":[[[-85.904,42.897],[-85.905,42.897],[-85.911,42.898],[-85.916,42.895],[-85.916,42.895],[-85.909,42.893],[-85.907,42.894],[-85.904,42.897]]]},"properties":{"OBJECTID":1004043,"JOB_ID":"68cc2fb872ce440b981a6fa6","CUSTOMER_COUNT":19,"CREW_ASSIGNED":1,"GROUP_LEVEL":0,"NEEDS_UPDATED":0,"EST_TIME_RESTORATION":1758237300000,"CAUSE_CD":"5fa41397b71bb212402bcdf4","CAUSE_DESC":"Equipment Failure","OUTAGE_TIME":1758211770000,"HEADQUARTER":"GRA","SHAPE.STArea()":299160.27334165794,"SHAPE.STLength()":2324.939717335993}},{"type":"Feature","id":1004082,"geometry":{"type":"Polygon","coordinates":[[[-84.389,42.722],[-84.39,42.725],[-84.391,42.73],[-84.394,42.73],[-84.394,42.729],[-84.395,42.727],[-84.396,42.72],[-84.393,42.719],[-84.392,42.719],[-84.389,42.722]]]},"properties":{"OBJECTID":1004082,"JOB_ID":"68cc51df95eafa4668c5a5d3","CUSTOMER_COUNT":44,"CREW_ASSIGNED":1,"GROUP_LEVEL":0,"NEEDS_UPDATED":0,"EST_TIME_RESTORATION":1758238200000,"CAUSE_CD":null,"CAUSE_DESC":null,"OUTAGE_TIME":1758220762000,"HEADQUARTER":"LAN","SHAPE.STArea()":485082.40251389425,"SHAPE.STLength()":2906.2000540483396}},{"type":"Feature","id":1004102,"geometry":{"type":"Polygon","coordinates":[[[-84.326,43.934],[-84.325,43.934],[-84.325,43.934],[-84.325,43.934],[-84.325,43.934],[-84.325,43.934],[-84.324,43.934],[-84.324,43.934],[-84.324,43.934],[-84.324,43.934],[-84.324,43.935],[-84.324,43.935],[-84.324,43.935],[-84.324,43.935],[-84.324,43.935],[-84.324,43.935],[-84.324,43.935],[-84.324,43.936],[-84.324,43.936],[-84.324,43.936],[-84.324,43.936],[-84.324,43.936],[-84.324,43.936],[-84.325,43.937],[-84.325,43.937],[-84.325,43.937],[-84.326,43.937],[-84.326,43.937],[-84.326,43.937],[-84.326,43.937],[-84.327,43.937],[-84.327,43.937],[-84.327,43.937],[-84.327,43.937],[-84.327,43.936],[-84.327,43.936],[-84.328,43.936],[-84.328,43.936],[-84.328,43.936],[-84.328,43.936],[-84.328,43.936],[-84.328,43.935],[-84.328,43.935],[-84.328,43.935],[-84.328,43.935],[-84.327,43.935],[-84.327,43.935],[-84.327,43.934],[-84.327,43.934],[-84.327,43.934],[-84.326,43.934],[-84.326,43.934],[-84.326,43.934]]]},"properties":{"OBJECTID":1004102,"JOB_ID":"68cc62b995eafa4668c5c9cc","CUSTOMER_COUNT":2,"CREW_ASSIGNED":1,"GROUP_LEVEL":0,"NEEDS_UPDATED":0,"EST_TIME_RESTORATION":1758238200000,"CAUSE_CD":null,"CAUSE_DESC":null,"OUTAGE_TIME":1758224439000,"HEADQUARTER":"CLR","SHAPE.STArea()":83818.496560358195,"SHAPE.STLength()":1031.7208103045391}},{"type":"Feature","id":1004106,"geometry":{"type":"Polygon","coordinates":[[[-84.704,44.375],[-84.703,44.375],[-84.703,44.375],[-84.703,44.375],[-84.703,44.375],[-84.703,44.375],[-84.703,44.376],[-84.703,44.376],[-84.703,44.376],[-84.703,44.376],[-84.703,44.376],[-84.703,44.376],[-84.702,44.376],[-84.702,44.376],[-84.702,44.376],[-84.702,44.376],[-84.702,44.376],[-84.702,44.377],[-84.702,44.377],[-84.702,44.377],[-84.702,44.377],[-84.702,44.377],[-84.702,44.377],[-84.702,44.377],[-84.702,44.377],[-84.702,44.377],[-84.702,44.377],[-84.702,44.377],[-84.702,44.377],[-84.702,44.377],[-84.702,44.377],[-84.702,44.377],[-84.702,44.377],[-84.702,44.378],[-84.703,44.378],[-84.703,44.378],[-84.704,44.378],[-84.704,44.378],[-84.704,44.378],[-84.704,44.378],[-84.704,44.378],[-84.704,44.378],[-84.704,44.378],[-84.704,44.378],[-84.704,44.378],[-84.704,44.378],[-84.705,44.378],[-84.705,44.378],[-84.705,44.378],[-84.705,44.378],[-84.705,44.378],[-84.705,44.378],[-84.705,44.378],[-84.705,44.378],[-84.705,44.378],[-84.705,44.378],[-84.705,44.378],[-84.705,44.378],[-84.706,44.378],[-84.706,44.378],[-84.706,44.378],[-84.706,44.378],[-84.706,44.378],[-84.706,44.378],[-84.706,44.378],[-84.706,44.377],[-84.706,44.377],[-84.706,44.376],[-84.706,44.376],[-84.706,44.376],[-84.706,44.376],[-84.706,44.376],[-84.706,44.376],[-84.706,44.376],[-84.706,44.376],[-84.706,44.376],[-84.706,44.376],[-84.705,44.376],[-84.705,44.376],[-84.705,44.376],[-84.705,44.376],[-84.705,44.376],[-84.705,44.376],[-84.705,44.376],[-84.705,44.376],[-84.705,44.376],[-84.705,44.376],[-84.705,44.376],[-84.705,44.376],[-84.705,44.376],[-84.705,44.376],[-84.705,44.376],[-84.705,44.376],[-84.705,44.375],[-84.705,44.375],[-84.705,44.375],[-84.705,44.375],[-84.704,44.375],[-84.704,44.375],[-84.704,44.375],[-84.704,44.375],[-84.704,44.375]]]},"properties":{"OBJECTID":1004106,"JOB_ID":"68cc644595eafa4668c5eff7","CUSTOMER_COUNT":5,"CREW_ASSIGNED":0,"GROUP_LEVEL":0,"NEEDS_UPDATED":0,"EST_TIME_RESTORATION":1758260700000,"CAUSE_CD":null,"CAUSE_DESC":null,"OUTAGE_TIME":1758225165000,"HEADQUARTER":"WBR","SHAPE.STArea()":80212.407630235015,"SHAPE.STLength()":1021.4233251589105}},{"type":"Feature","id":1004107,"geometry":{"type":"Polygon","coordinates":[[[-84.307,43.82],[-84.308,43.821],[-84.321,43.817],[-84.326,43.814],[-84.322,43.813],[-84.32,43.813],[-84.311,43.814],[-84.309,43.815],[-84.308,43.819],[-84.307,43.82]]]},"properties":{"OBJECTID":1004107,"JOB_ID":"68cc650695eafa4668c5f82f","CUSTOMER_COUNT":19,"CREW_ASSIGNED":1,"GROUP_LEVEL":0,"NEEDS_UPDATED":0,"EST_TIME_RESTORATION":1758253500000,"CAUSE_CD":null,"CAUSE_DESC":null,"OUTAGE_TIME":1758225405000,"HEADQUARTER":"MDL","SHAPE.STArea()":697748.00374262477,"SHAPE.STLength()":3839.12899611784}},{"type":"Feature","id":1004108,"geometry":{"type":"Polygon","coordinates":[[[-84.793,44.389],[-84.793,44.389],[-84.793,44.389],[-84.793,44.389],[-84.792,44.389],[-84.792,44.389],[-84.792,44.389],[-84.792,44.389],[-84.792,44.389],[-84.792,44.39],[-84.791,44.39],[-84.791,44.39],[-84.791,44.39],[-84.792,44.391],[-84.792,44.391],[-84.792,44.391],[-84.792,44.391],[-84.792,44.391],[-84.792,44.392],[-84.793,44.392],[-84.793,44.392],[-84.793,44.392],[-84.793,44.392],[-84.793,44.392],[-84.794,44.392],[-84.794,44.392],[-84.794,44.392],[-84.795,44.391],[-84.795,44.391],[-84.795,44.391],[-84.795,44.391],[-84.795,44.391],[-84.795,44.391],[-84.795,44.39],[-84.795,44.39],[-84.795,44.39],[-84.795,44.39],[-84.795,44.389],[-84.795,44.389],[-84.794,44.389],[-84.794,44.389],[-84.794,44.389],[-84.794,44.389],[-84.794,44.389],[-84.793,44.389]]]},"properties":{"OBJECTID":1004108,"JOB_ID":"68cc658995eafa4668c5fa14","CUSTOMER_COUNT":2,"CREW_ASSIGNED":0,"GROUP_LEVEL":0,"NEEDS_UPDATED":0,"EST_TIME_RESTORATION":1758246300000,"CAUSE_CD":null,"CAUSE_DESC":null,"OUTAGE_TIME":1758225165000,"HEADQUARTER":"WBR","SHAPE.STArea()":80514.025639665677,"SHAPE.STLength()":1009.1342413965784}},{"type":"Feature","id":1004109,"geometry":{"type":"Polygon","coordinates":[[[-84.755,44.393],[-84.754,44.393],[-84.754,44.393],[-84.754,44.393],[-84.754,44.393],[-84.754,44.393],[-84.754,44.393],[-84.754,44.393],[-84.754,44.393],[-84.754,44.393],[-84.754,44.394],[-84.754,44.394],[-84.754,44.394],[-84.754,44.394],[-84.754,44.394],[-84.753,44.394],[-84.753,44.394],[-84.753,44.394],[-84.753,44.394],[-84.752,44.394],[-84.752,44.395],[-84.752,44.395],[-84.752,44.395],[-84.752,44.395],[-84.752,44.395],[-84.752,44.395],[-84.752,44.395],[-84.752,44.395],[-84.752,44.395],[-84.752,44.395],[-84.752,44.395],[-84.752,44.395],[-84.752,44.395],[-84.752,44.396],[-84.752,44.396],[-84.752,44.396],[-84.753,44.396],[-84.753,44.396],[-84.753,44.396],[-84.753,44.396],[-84.753,44.396],[-84.753,44.396],[-84.753,44.396],[-84.753,44.396],[-84.753,44.396],[-84.753,44.396],[-84.753,44.396],[-84.754,44.396],[-84.754,44.396],[-84.754,44.396],[-84.755,44.396],[-84.755,44.396],[-84.755,44.396],[-84.755,44.396],[-84.755,44.396],[-84.755,44.396],[-84.755,44.396],[-84.756,44.396],[-84.756,44.396],[-84.756,44.396],[-84.756,44.396],[-84.756,44.396],[-84.756,44.396],[-84.756,44.396],[-84.756,44.396],[-84.756,44.396],[-84.756,44.396],[-84.756,44.396],[-84.756,44.396],[-84.756,44.396],[-84.756,44.395],[-84.756,44.395],[-84.756,44.395],[-84.756,44.395],[-84.756,44.395],[-84.756,44.395],[-84.756,44.395],[-84.756,44.395],[-84.756,44.395],[-84.756,44.395],[-84.756,44.395],[-84.756,44.395],[-84.756,44.395],[-84.756,44.394],[-84.756,44.394],[-84.756,44.394],[-84.756,44.394],[-84.756,44.394],[-84.756,44.394],[-84.756,44.394],[-84.755,44.394],[-84.755,44.394],[-84.755,44.394],[-84.755,44.393],[-84.755,44.393],[-84.755,44.393],[-84.755,44.393],[-84.755,44.393],[-84.755,44.393],[-84.755,44.393]]]},"properties":{"OBJECTID":1004109,"JOB_ID":"68cc658995eafa4668c5fa17","CUSTOMER_COUNT":7,"CREW_ASSIGNED":0,"GROUP_LEVEL":0,"NEEDS_UPDATED":0,"EST_TIME_RESTORATION":1758258900000,"CAUSE_CD":null,"CAUSE_DESC":null,"OUTAGE_TIME":1758225165000,"HEADQUARTER":"WBR","SHAPE.STArea()":80590.589807584547,"SHAPE.STLength()":1020.5094726659387}},{"type":"Feature","id":1004110,"geometry":{"type":"Polygon","coordinates":[[[-84.79,44.4],[-84.79,44.4],[-84.79,44.4],[-84.79,44.4],[-84.789,44.4],[-84.789,44.4],[-84.789,44.4],[-84.789,44.4],[-84.789,44.4],[-84.789,44.4],[-84.789,44.4],[-84.789,44.4],[-84.788,44.4],[-84.788,44.4],[-84.788,44.4],[-84.788,44.4],[-84.788,44.4],[-84.788,44.4],[-84.788,44.4],[-84.788,44.401],[-84.788,44.401],[-84.787,44.401],[-84.787,44.401],[-84.787,44.401],[-84.787,44.401],[-84.787,44.401],[-84.787,44.401],[-84.787,44.401],[-84.787,44.402],[-84.787,44.402],[-84.787,44.402],[-84.787,44.402],[-84.787,44.402],[-84.787,44.402],[-84.787,44.402],[-84.787,44.402],[-84.787,44.402],[-84.787,44.402],[-84.787,44.402],[-84.787,44.402],[-84.787,44.402],[-84.787,44.402],[-84.787,44.402],[-84.787,44.402],[-84.787,44.402],[-84.788,44.402],[-84.788,44.402],[-84.788,44.403],[-84.788,44.403],[-84.788,44.403],[-84.788,44.403],[-84.788,44.403],[-84.788,44.403],[-84.788,44.403],[-84.789,44.403],[-84.789,44.403],[-84.789,44.403],[-84.789,44.403],[-84.789,44.403],[-84.789,44.403],[-84.789,44.403],[-84.789,44.403],[-84.79,44.403],[-84.79,44.403],[-84.79,44.403],[-84.79,44.403],[-84.79,44.403],[-84.79,44.403],[-84.79,44.403],[-84.79,44.403],[-84.79,44.402],[-84.79,44.402],[-84.79,44.402],[-84.791,44.402],[-84.791,44.402],[-84.791,44.402],[-84.791,44.402],[-84.791,44.402],[-84.791,44.402],[-84.791,44.401],[-84.791,44.401],[-84.791,44.401],[-84.791,44.401],[-84.791,44.401],[-84.791,44.401],[-84.791,44.401],[-84.791,44.401],[-84.791,44.401],[-84.791,44.401],[-84.791,44.401],[-84.791,44.401],[-84.791,44.401],[-84.791,44.4],[-84.791,44.4],[-84.791,44.4],[-84.791,44.4],[-84.791,44.4],[-84.791,44.4],[-84.791,44.4],[-84.791,44.4],[-84.79,44.4],[-84.79,44.4],[-84.79,44.4],[-84.79,44.4],[-84.79,44.4],[-84.79,44.4],[-84.79,44.4]]]},"properties":{"OBJECTID":1004110,"JOB_ID":"68cc658995eafa4668c5fa1a","CUSTOMER_COUNT":11,"CREW_ASSIGNED":0,"GROUP_LEVEL":0,"NEEDS_UPDATED":0,"EST_TIME_RESTORATION":1758245400000,"CAUSE_CD":null,"CAUSE_DESC":null,"OUTAGE_TIME":1758225165000,"HEADQUARTER":"WBR","SHAPE.STArea()":79573.000149483822,"SHAPE.STLength()":1016.5527715318628}},{"type":"Feature","id":1004115,"geometry":{"type":"Polygon","coordinates":[[[-84.325,43.872],[-84.325,43.872],[-84.325,43.872],[-84.325,43.872],[-84.325,43.872],[-84.324,43.872],[-84.324,43.872],[-84.324,43.872],[-84.324,43.873],[-84.324,43.873],[-84.324,43.873],[-84.324,43.873],[-84.324,43.873],[-84.324,43.873],[-84.324,43.873],[-84.324,43.873],[-84.324,43.873],[-84.323,43.874],[-84.323,43.874],[-84.323,43.874],[-84.323,43.875],[-84.323,43.875],[-84.323,43.875],[-84.323,43.875],[-84.323,43.875],[-84.323,43.875],[-84.323,43.875],[-84.323,43.875],[-84.323,43.875],[-84.323,43.875],[-84.323,43.875],[-84.323,43.875],[-84.324,43.875],[-84.324,43.875],[-84.324,43.876],[-84.324,43.876],[-84.324,43.876],[-84.324,43.876],[-84.324,43.876],[-84.324,43.876],[-84.324,43.876],[-84.324,43.876],[-84.324,43.876],[-84.324,43.876],[-84.325,43.876],[-84.325,43.876],[-84.325,43.876],[-84.325,43.876],[-84.325,43.876],[-84.325,43.876],[-84.325,43.876],[-84.325,43.876],[-84.325,43.876],[-84.326,43.876],[-84.326,43.875],[-84.326,43.875],[-84.326,43.875],[-84.326,43.875],[-84.326,43.875],[-84.326,43.875],[-84.326,43.875],[-84.326,43.875],[-84.327,43.874],[-84.327,43.874],[-84.327,43.874],[-84.327,43.874],[-84.327,43.874],[-84.327,43.874],[-84.327,43.874],[-84.327,43.873],[-84.327,43.873],[-84.327,43.873],[-84.327,43.873],[-84.327,43.873],[-84.327,43.873],[-84.327,43.873],[-84.327,43.873],[-84.326,43.873],[-84.326,43.873],[-84.326,43.873],[-84.326,43.873],[-84.326,43.873],[-84.326,43.873],[-84.326,43.873],[-84.326,43.872],[-84.326,43.872],[-84.325,43.872],[-84.325,43.872],[-84.325,43.872],[-84.325,43.872],[-84.325,43.872],[-84.325,43.872],[-84.325,43.872]]]},"properties":{"OBJECTID":1004115,"JOB_ID":"68cc66c395eafa4668c6041b","CUSTOMER_COUNT":11,"CREW_ASSIGNED":1,"GROUP_LEVEL":0,"NEEDS_UPDATED":0,"EST_TIME_RESTORATION":1758246300000,"CAUSE_CD":null,"CAUSE_DESC":null,"OUTAGE_TIME":1758226110000,"HEADQUARTER":"MDL","SHAPE.STArea()":86463.916483302193,"SHAPE.STLength()":1074.178471567606}},{"type":"Feature","id":1004117,"geometry":{"type":"Polygon","coordinates":[[[-84.426,43.976],[-84.426,43.976],[-84.425,43.976],[-84.425,43.976],[-84.425,43.976],[-84.425,43.977],[-84.424,43.977],[-84.424,43.977],[-84.424,43.977],[-84.424,43.978],[-84.424,43.978],[-84.425,43.978],[-84.425,43.978],[-84.425,43.979],[-84.425,43.979],[-84.426,43.979],[-84.426,43.979],[-84.426,43.979],[-84.427,43.979],[-84.427,43.979],[-84.427,43.978],[-84.428,43.978],[-84.428,43.978],[-84.428,43.978],[-84.428,43.977],[-84.428,43.977],[-84.428,43.977],[-84.428,43.977],[-84.427,43.976],[-84.427,43.976],[-84.427,43.976],[-84.426,43.976],[-84.426,43.976]]]},"properties":{"OBJECTID":1004117,"JOB_ID":"68cc68f495eafa4668c60785","CUSTOMER_COUNT":1,"CREW_ASSIGNED":1,"GROUP_LEVEL":0,"NEEDS_UPDATED":0,"EST_TIME_RESTORATION":1758240000000,"CAUSE_CD":null,"CAUSE_DESC":null,"OUTAGE_TIME":1758226672000,"HEADQUARTER":"CLR","SHAPE.STArea()":70232.520500475992,"SHAPE.STLength()":940.96457780973253}},{"type":"Feature","id":1004118,"geometry":{"type":"Polygon","coordinates":[[[-84.875,43.938],[-84.875,43.938],[-84.874,43.938],[-84.874,43.938],[-84.874,43.938],[-84.873,43.939],[-84.873,43.939],[-84.873,43.939],[-84.873,43.939],[-84.873,43.94],[-84.873,43.94],[-84.873,43.94],[-84.874,43.94],[-84.874,43.941],[-84.874,43.941],[-84.875,43.941],[-84.875,43.941],[-84.875,43.941],[-84.876,43.941],[-84.876,43.941],[-84.876,43.94],[-84.877,43.94],[-84.877,43.94],[-84.877,43.94],[-84.877,43.939],[-84.877,43.939],[-84.877,43.939],[-84.877,43.939],[-84.876,43.938],[-84.876,43.938],[-84.876,43.938],[-84.875,43.938],[-84.875,43.938]]]},"properties":{"OBJECTID":1004118,"JOB_ID":"68cc691e95eafa4668c607a4","CUSTOMER_COUNT":1,"CREW_ASSIGNED":1,"GROUP_LEVEL":0,"NEEDS_UPDATED":0,"EST_TIME_RESTORATION":1758240000000,"CAUSE_CD":"5fa41397b71bb212402bcdec","CAUSE_DESC":"Trees","OUTAGE_TIME":1758226713000,"HEADQUARTER":"CLR","SHAPE.STArea()":70232.514574235727,"SHAPE.STLength()":940.96453811014055}},{"type":"Feature","id":1004120,"geometry":{"type":"Polygon","coordinates":[[[-84.231,43.631],[-84.231,43.631],[-84.23,43.631],[-84.23,43.631],[-84.23,43.631],[-84.23,43.631],[-84.229,43.631],[-84.229,43.632],[-84.229,43.632],[-84.229,43.632],[-84.229,43.633],[-84.23,43.633],[-84.23,43.633],[-84.23,43.633],[-84.23,43.633],[-84.231,43.633],[-84.231,43.633],[-84.231,43.633],[-84.232,43.633],[-84.232,43.633],[-84.232,43.633],[-84.233,43.633],[-84.233,43.633],[-84.233,43.632],[-84.233,43.632],[-84.233,43.632],[-84.233,43.632],[-84.233,43.631],[-84.232,43.631],[-84.232,43.631],[-84.232,43.631],[-84.232,43.631],[-84.231,43.631]]]},"properties":{"OBJECTID":1004120,"JOB_ID":"68cc6c2a95eafa4668c62403","CUSTOMER_COUNT":1,"CREW_ASSIGNED":1,"GROUP_LEVEL":0,"NEEDS_UPDATED":0,"EST_TIME_RESTORATION":1758244500000,"CAUSE_CD":null,"CAUSE_DESC":null,"OUTAGE_TIME":1758227493000,"HEADQUARTER":"MDL","SHAPE.STArea()":70232.518419456086,"SHAPE.STLength()":940.9645638691261}},{"type":"Feature","id":1004123,"geometry":{"type":"Polygon","coordinates":[[[-84.251,43.648],[-84.251,43.648],[-84.248,43.648],[-84.248,43.648],[-84.248,43.648],[-84.248,43.648],[-84.248,43.648],[-84.248,43.648],[-84.248,43.649],[-84.248,43.649],[-84.248,43.649],[-84.248,43.649],[-84.248,43.649],[-84.247,43.649],[-84.247,43.649],[-84.247,43.649],[-84.247,43.649],[-84.247,43.649],[-84.247,43.649],[-84.247,43.649],[-84.247,43.649],[-84.247,43.649],[-84.247,43.649],[-84.247,43.649],[-84.247,43.649],[-84.247,43.649],[-84.247,43.649],[-84.247,43.649],[-84.247,43.649],[-84.247,43.649],[-84.247,43.649],[-84.247,43.649],[-84.247,43.649],[-84.247,43.649],[-84.247,43.649],[-84.247,43.649],[-84.247,43.65],[-84.247,43.65],[-84.247,43.65],[-84.247,43.65],[-84.247,43.65],[-84.247,43.65],[-84.247,43.65],[-84.247,43.65],[-84.247,43.65],[-84.247,43.65],[-84.247,43.65],[-84.247,43.65],[-84.247,43.65],[-84.247,43.65],[-84.247,43.65],[-84.247,43.65],[-84.247,43.65],[-84.247,43.65],[-84.247,43.65],[-84.247,43.65],[-84.248,43.65],[-84.248,43.65],[-84.248,43.65],[-84.248,43.65],[-84.248,43.65],[-84.248,43.65],[-84.248,43.65],[-84.248,43.65],[-84.248,43.65],[-84.248,43.65],[-84.248,43.65],[-84.252,43.65],[-84.252,43.65],[-84.257,43.65],[-84.257,43.65],[-84.258,43.65],[-84.258,43.65],[-84.258,43.65],[-84.258,43.65],[-84.258,43.65],[-84.258,43.65],[-84.258,43.65],[-84.258,43.65],[-84.258,43.65],[-84.258,43.65],[-84.258,43.65],[-84.258,43.65],[-84.258,43.65],[-84.258,43.65],[-84.258,43.65],[-84.258,43.65],[-84.258,43.65],[-84.258,43.65],[-84.258,43.65],[-84.259,43.65],[-84.259,43.65],[-84.259,43.65],[-84.259,43.65],[-84.259,43.65],[-84.259,43.65],[-84.259,43.65],[-84.259,43.65],[-84.259,43.65],[-84.259,43.65],[-84.259,43.649],[-84.259,43.649],[-84.259,43.649],[-84.259,43.649],[-84.259,43.649],[-84.259,43.649],[-84.259,43.649],[-84.259,43.649],[-84.259,43.649],[-84.259,43.649],[-84.259,43.649],[-84.259,43.649],[-84.259,43.649],[-84.258,43.649],[-84.258,43.649],[-84.258,43.649],[-84.258,43.649],[-84.258,43.649],[-84.258,43.649],[-84.258,43.649],[-84.258,43.649],[-84.258,43.649],[-84.258,43.649],[-84.258,43.649],[-84.258,43.649],[-84.258,43.649],[-84.258,43.649],[-84.258,43.648],[-84.258,43.648],[-84.258,43.648],[-84.258,43.648],[-84.258,43.648],[-84.257,43.648],[-84.257,43.648],[-84.251,43.648]]]},"properties":{"OBJECTID":1004123,"JOB_ID":"68cc6cc395eafa4668c62580","CUSTOMER_COUNT":24,"CREW_ASSIGNED":1,"GROUP_LEVEL":0,"NEEDS_UPDATED":0,"EST_TIME_RESTORATION":1758259800000,"CAUSE_CD":null,"CAUSE_DESC":null,"OUTAGE_TIME":1758227646000,"HEADQUARTER":"MDL","SHAPE.STArea()":201668.17501287209,"SHAPE.STLength()":2156.3254582179406}},{"type":"Feature","id":1004124,"geometry":{"type":"Polygon","coordinates":[[[-84.225,43.628],[-84.225,43.628],[-84.224,43.628],[-84.224,43.628],[-84.224,43.628],[-84.224,43.628],[-84.224,43.628],[-84.224,43.628],[-84.224,43.628],[-84.224,43.628],[-84.223,43.628],[-84.223,43.628],[-84.223,43.628],[-84.223,43.628],[-84.223,43.628],[-84.223,43.628],[-84.223,43.628],[-84.223,43.628],[-84.223,43.628],[-84.223,43.628],[-84.223,43.628],[-84.223,43.628],[-84.223,43.629],[-84.223,43.629],[-84.223,43.629],[-84.223,43.629],[-84.223,43.629],[-84.223,43.629],[-84.223,43.629],[-84.223,43.629],[-84.223,43.629],[-84.223,43.629],[-84.223,43.629],[-84.223,43.629],[-84.223,43.629],[-84.223,43.63],[-84.223,43.63],[-84.223,43.63],[-84.223,43.63],[-84.224,43.63],[-84.224,43.63],[-84.224,43.63],[-84.224,43.63],[-84.224,43.63],[-84.224,43.63],[-84.224,43.63],[-84.224,43.63],[-84.224,43.63],[-84.224,43.63],[-84.224,43.63],[-84.224,43.63],[-84.225,43.63],[-84.225,43.63],[-84.225,43.63],[-84.225,43.63],[-84.225,43.63],[-84.226,43.63],[-84.226,43.63],[-84.226,43.63],[-84.226,43.63],[-84.226,43.63],[-84.226,43.63],[-84.226,43.63],[-84.226,43.63],[-84.226,43.63],[-84.226,43.63],[-84.226,43.63],[-84.226,43.63],[-84.226,43.63],[-84.226,43.63],[-84.226,43.63],[-84.226,43.63],[-84.227,43.63],[-84.227,43.63],[-84.227,43.63],[-84.227,43.63],[-84.227,43.63],[-84.227,43.629],[-84.227,43.629],[-84.227,43.629],[-84.227,43.629],[-84.227,43.629],[-84.227,43.629],[-84.227,43.629],[-84.227,43.629],[-84.227,43.629],[-84.227,43.629],[-84.227,43.629],[-84.227,43.629],[-84.227,43.629],[-84.227,43.628],[-84.227,43.628],[-84.227,43.628],[-84.227,43.628],[-84.227,43.628],[-84.227,43.628],[-84.227,43.628],[-84.227,43.628],[-84.226,43.628],[-84.226,43.628],[-84.226,43.628],[-84.226,43.628],[-84.226,43.628],[-84.226,43.628],[-84.226,43.628],[-84.226,43.628],[-84.226,43.628],[-84.226,43.628],[-84.226,43.628],[-84.226,43.628],[-84.226,43.628],[-84.226,43.628],[-84.226,43.628],[-84.226,43.628],[-84.225,43.628],[-84.225,43.628],[-84.225,43.628],[-84.225,43.628]]]},"properties":{"OBJECTID":1004124,"JOB_ID":"68cc6dfb95eafa4668c6276a","CUSTOMER_COUNT":8,"CREW_ASSIGNED":1,"GROUP_LEVEL":0,"NEEDS_UPDATED":0,"EST_TIME_RESTORATION":1758240900000,"CAUSE_CD":null,"CAUSE_DESC":null,"OUTAGE_TIME":1758227325000,"HEADQUARTER":"MDL","SHAPE.STArea()":78245.985104628198,"SHAPE.STLength()":999.40596626176409}},{"type":"Feature","id":1004127,"geometry":{"type":"Polygon","coordinates":[[[-84.928,43.871],[-84.928,43.871],[-84.928,43.871],[-84.927,43.871],[-84.927,43.871],[-84.927,43.871],[-84.927,43.871],[-84.926,43.872],[-84.926,43.872],[-84.926,43.872],[-84.927,43.872],[-84.927,43.873],[-84.927,43.873],[-84.927,43.873],[-84.928,43.873],[-84.928,43.873],[-84.928,43.873],[-84.929,43.873],[-84.929,43.873],[-84.929,43.873],[-84.93,43.873],[-84.93,43.873],[-84.93,43.872],[-84.93,43.872],[-84.93,43.872],[-84.93,43.872],[-84.93,43.871],[-84.93,43.871],[-84.93,43.871],[-84.929,43.871],[-84.929,43.871],[-84.929,43.871],[-84.928,43.871]]]},"properties":{"OBJECTID":1004127,"JOB_ID":"68cc703f95eafa4668c62c5c","CUSTOMER_COUNT":1,"CREW_ASSIGNED":1,"GROUP_LEVEL":0,"NEEDS_UPDATED":0,"EST_TIME_RESTORATION":1758242700000,"CAUSE_CD":null,"CAUSE_DESC":null,"OUTAGE_TIME":1758228540000,"HEADQUARTER":"CLR","SHAPE.STArea()":70232.51431126229,"SHAPE.STLength()":940.96453634842203}},{"type":"Feature","id":1004132,"geometry":{"type":"Polygon","coordinates":[[[-84.011,43.443],[-84.011,43.444],[-84.013,43.444],[-84.014,43.444],[-84.014,43.444],[-84.015,43.443],[-84.015,43.441],[-84.015,43.441],[-84.014,43.441],[-84.014,43.441],[-84.012,43.441],[-84.011,43.443]]]},"properties":{"OBJECTID":1004132,"JOB_ID":"68cc70d895eafa4668c632c5","CUSTOMER_COUNT":63,"CREW_ASSIGNED":1,"GROUP_LEVEL":1,"NEEDS_UPDATED":0,"EST_TIME_RESTORATION":1758248100000,"CAUSE_CD":null,"CAUSE_DESC":null,"OUTAGE_TIME":1758228525000,"HEADQUARTER":"SAG","SHAPE.STArea()":77942.223369936837,"SHAPE.STLength()":1088.3671472068697}},{"type":"Feature","id":1004133,"geometry":{"type":"Polygon","coordinates":[[[-84.019,43.68],[-84.018,43.68],[-84.018,43.68],[-84.018,43.68],[-84.018,43.68],[-84.018,43.68],[-84.017,43.681],[-84.017,43.681],[-84.017,43.681],[-84.017,43.681],[-84.017,43.681],[-84.017,43.681],[-84.017,43.681],[-84.017,43.681],[-84.017,43.682],[-84.017,43.682],[-84.016,43.682],[-84.016,43.682],[-84.016,43.682],[-84.016,43.682],[-84.016,43.683],[-84.016,43.683],[-84.017,43.683],[-84.017,43.683],[-84.017,43.684],[-84.017,43.684],[-84.018,43.684],[-84.018,43.684],[-84.018,43.684],[-84.018,43.684],[-84.019,43.684],[-84.019,43.684],[-84.019,43.684],[-84.019,43.684],[-84.019,43.683],[-84.02,43.683],[-84.02,43.683],[-84.02,43.683],[-84.02,43.683],[-84.02,43.683],[-84.02,43.683],[-84.02,43.682],[-84.02,43.682],[-84.02,43.682],[-84.02,43.682],[-84.02,43.682],[-84.02,43.681],[-84.02,43.681],[-84.02,43.681],[-84.02,43.681],[-84.02,43.68],[-84.019,43.68],[-84.019,43.68],[-84.019,43.68]]]},"properties":{"OBJECTID":1004133,"JOB_ID":"68cc70e895eafa4668c634ac","CUSTOMER_COUNT":2,"CREW_ASSIGNED":0,"GROUP_LEVEL":0,"NEEDS_UPDATED":0,"EST_TIME_RESTORATION":1758250800000,"CAUSE_CD":"5fa41397b71bb212402bcdf5","CAUSE_DESC":"Weather","OUTAGE_TIME":1758228465000,"HEADQUARTER":"BCY","SHAPE.STArea()":101304.67078328109,"SHAPE.STLength()":1156.9707262191494}},{"type":"Feature","id":1004135,"geometry":{"type":"Polygon","coordinates":[[[-85.457,44.215],[-85.457,44.215],[-85.456,44.215],[-85.456,44.215],[-85.456,44.215],[-85.456,44.215],[-85.455,44.216],[-85.455,44.216],[-85.455,44.216],[-85.455,44.216],[-85.455,44.217],[-85.456,44.217],[-85.456,44.217],[-85.456,44.217],[-85.456,44.217],[-85.457,44.217],[-85.457,44.218],[-85.458,44.217],[-85.458,44.217],[-85.458,44.217],[-85.458,44.217],[-85.459,44.217],[-85.459,44.217],[-85.459,44.216],[-85.459,44.216],[-85.459,44.216],[-85.459,44.216],[-85.459,44.215],[-85.458,44.215],[-85.458,44.215],[-85.458,44.215],[-85.458,44.215],[-85.457,44.215]]]},"properties":{"OBJECTID":1004135,"JOB_ID":"68cc72b495eafa4668c63d12","CUSTOMER_COUNT":1,"CREW_ASSIGNED":1,"GROUP_LEVEL":0,"NEEDS_UPDATED":0,"EST_TIME_RESTORATION":1758247200000,"CAUSE_CD":"5fa41397b71bb212402bcdf8","CAUSE_DESC":"Other","OUTAGE_TIME":1758229167000,"HEADQUARTER":"CAD","SHAPE.STArea()":70232.518419456086,"SHAPE.STLength()":940.9645638691261}},{"type":"Feature","id":1004136,"geometry":{"type":"Polygon","coordinates":[[[-83.839,43.604],[-83.839,43.604],[-83.839,43.604],[-83.839,43.604],[-83.839,43.604],[-83.839,43.604],[-83.839,43.604],[-83.839,43.604],[-83.839,43.604],[-83.839,43.604],[-83.839,43.604],[-83.839,43.604],[-83.839,43.604],[-83.838,43.604],[-83.838,43.604],[-83.838,43.604],[-83.838,43.604],[-83.838,43.604],[-83.838,43.604],[-83.838,43.604],[-83.838,43.604],[-83.838,43.604],[-83.838,43.604],[-83.838,43.604],[-83.838,43.604],[-83.838,43.604],[-83.838,43.604],[-83.838,43.604],[-83.838,43.604],[-83.838,43.605],[-83.838,43.605],[-83.838,43.605],[-83.838,43.605],[-83.838,43.605],[-83.838,43.605],[-83.838,43.605],[-83.838,43.605],[-83.838,43.605],[-83.838,43.606],[-83.838,43.606],[-83.838,43.606],[-83.838,43.606],[-83.838,43.606],[-83.838,43.606],[-83.839,43.606],[-83.839,43.606],[-83.839,43.606],[-83.839,43.606],[-83.839,43.606],[-83.839,43.606],[-83.84,43.606],[-83.84,43.606],[-83.84,43.606],[-83.84,43.606],[-83.84,43.606],[-83.84,43.606],[-83.84,43.606],[-83.841,43.606],[-83.841,43.606],[-83.841,43.606],[-83.841,43.606],[-83.841,43.606],[-83.841,43.606],[-83.841,43.606],[-83.841,43.606],[-83.841,43.606],[-83.841,43.606],[-83.841,43.606],[-83.841,43.606],[-83.841,43.606],[-83.841,43.606],[-83.842,43.606],[-83.842,43.606],[-83.842,43.606],[-83.842,43.606],[-83.842,43.606],[-83.842,43.605],[-83.842,43.605],[-83.842,43.605],[-83.842,43.605],[-83.842,43.605],[-83.842,43.605],[-83.842,43.605],[-83.842,43.605],[-83.842,43.605],[-83.842,43.605],[-83.842,43.605],[-83.842,43.605],[-83.842,43.605],[-83.842,43.604],[-83.842,43.604],[-83.841,43.604],[-83.841,43.604],[-83.841,43.604],[-83.841,43.604],[-83.841,43.604],[-83.841,43.604],[-83.841,43.604],[-83.841,43.604],[-83.841,43.604],[-83.84,43.604],[-83.84,43.604],[-83.84,43.604],[-83.84,43.604],[-83.84,43.604],[-83.84,43.604],[-83.84,43.604],[-83.84,43.604],[-83.839,43.604]]]},"properties":{"OBJECTID":1004136,"JOB_ID":"68cc730395eafa4668c63db0","CUSTOMER_COUNT":5,"CREW_ASSIGNED":1,"GROUP_LEVEL":0,"NEEDS_UPDATED":0,"EST_TIME_RESTORATION":1758252600000,"CAUSE_CD":null,"CAUSE_DESC":null,"OUTAGE_TIME":1758228765000,"HEADQUARTER":"BCY","SHAPE.STArea()":78287.86466280515,"SHAPE.STLength()":999.04986091927344}},{"type":"Feature","id":1004141,"geometry":{"type":"Polygon","coordinates":[[[-84.028,43.681],[-84.028,43.681],[-84.027,43.681],[-84.027,43.681],[-84.027,43.681],[-84.027,43.681],[-84.026,43.682],[-84.026,43.682],[-84.026,43.682],[-84.026,43.682],[-84.026,43.683],[-84.026,43.683],[-84.027,43.683],[-84.027,43.683],[-84.027,43.683],[-84.028,43.684],[-84.028,43.684],[-84.028,43.684],[-84.029,43.683],[-84.029,43.683],[-84.029,43.683],[-84.03,43.683],[-84.03,43.683],[-84.03,43.683],[-84.03,43.682],[-84.03,43.682],[-84.03,43.682],[-84.03,43.681],[-84.029,43.681],[-84.029,43.681],[-84.029,43.681],[-84.028,43.681],[-84.028,43.681]]]},"properties":{"OBJECTID":1004141,"JOB_ID":"68cc73e795eafa4668c64000","CUSTOMER_COUNT":1,"CREW_ASSIGNED":0,"GROUP_LEVEL":0,"NEEDS_UPDATED":0,"EST_TIME_RESTORATION":1758245400000,"CAUSE_CD":"5fa41397b71bb212402bcdf5","CAUSE_DESC":"Weather","OUTAGE_TIME":1758229473000,"HEADQUARTER":"BCY","SHAPE.STArea()":70232.510466041931,"SHAPE.STLength()":940.96451058958166}},{"type":"Feature","id":1004142,"geometry":{"type":"Polygon","coordinates":[[[-84.027,44.062],[-84.027,44.062],[-84.026,44.063],[-84.026,44.063],[-84.026,44.063],[-84.026,44.063],[-84.025,44.063],[-84.025,44.063],[-84.025,44.064],[-84.025,44.064],[-84.025,44.064],[-84.025,44.065],[-84.026,44.065],[-84.026,44.065],[-84.026,44.065],[-84.027,44.065],[-84.027,44.065],[-84.027,44.065],[-84.028,44.065],[-84.028,44.065],[-84.028,44.065],[-84.029,44.065],[-84.029,44.064],[-84.029,44.064],[-84.029,44.064],[-84.029,44.064],[-84.029,44.063],[-84.029,44.063],[-84.028,44.063],[-84.028,44.063],[-84.028,44.063],[-84.027,44.062],[-84.027,44.062]]]},"properties":{"OBJECTID":1004142,"JOB_ID":"68cc76b495eafa4668c645db","CUSTOMER_COUNT":1,"CREW_ASSIGNED":1,"GROUP_LEVEL":0,"NEEDS_UPDATED":0,"EST_TIME_RESTORATION":1758254400000,"CAUSE_CD":null,"CAUSE_DESC":null,"OUTAGE_TIME":1758230191000,"HEADQUARTER":"WBR","SHAPE.STArea()":70232.51431126229,"SHAPE.STLength()":940.96453634842169}},{"type":"Feature","id":1004143,"geometry":{"type":"Polygon","coordinates":[[[-86.446,44.038],[-86.446,44.038],[-86.446,44.038],[-86.445,44.038],[-86.445,44.039],[-86.445,44.039],[-86.445,44.039],[-86.445,44.039],[-86.445,44.04],[-86.445,44.04],[-86.445,44.04],[-86.445,44.04],[-86.445,44.04],[-86.445,44.041],[-86.446,44.041],[-86.446,44.041],[-86.446,44.041],[-86.447,44.041],[-86.447,44.041],[-86.448,44.041],[-86.448,44.04],[-86.448,44.04],[-86.448,44.04],[-86.448,44.04],[-86.448,44.04],[-86.448,44.039],[-86.448,44.039],[-86.448,44.039],[-86.448,44.039],[-86.448,44.038],[-86.447,44.038],[-86.447,44.038],[-86.446,44.038]]]},"properties":{"OBJECTID":1004143,"JOB_ID":"68cc76de95eafa4668c64623","CUSTOMER_COUNT":1,"CREW_ASSIGNED":1,"GROUP_LEVEL":0,"NEEDS_UPDATED":0,"EST_TIME_RESTORATION":1758245400000,"CAUSE_CD":null,"CAUSE_DESC":null,"OUTAGE_TIME":1758230234000,"HEADQUARTER":"LDG","SHAPE.STArea()":70232.516392280144,"SHAPE.STLength()":940.96455028908599}},{"type":"Feature","id":1004146,"geometry":{"type":"Polygon","coordinates":[[[-85.625,42.862],[-85.625,42.862],[-85.625,42.862],[-85.625,42.862],[-85.624,42.862],[-85.624,42.862],[-85.624,42.862],[-85.624,42.862],[-85.624,42.862],[-85.624,42.862],[-85.624,42.862],[-85.624,42.862],[-85.624,42.862],[-85.624,42.862],[-85.624,42.862],[-85.624,42.862],[-85.624,42.862],[-85.624,42.862],[-85.624,42.862],[-85.624,42.862],[-85.624,42.862],[-85.623,42.862],[-85.623,42.862],[-85.623,42.862],[-85.623,42.862],[-85.623,42.862],[-85.623,42.862],[-85.623,42.862],[-85.623,42.863],[-85.623,42.863],[-85.623,42.863],[-85.623,42.863],[-85.623,42.863],[-85.623,42.863],[-85.623,42.863],[-85.623,42.863],[-85.623,42.864],[-85.623,42.864],[-85.623,42.864],[-85.623,42.864],[-85.623,42.864],[-85.624,42.864],[-85.624,42.864],[-85.624,42.864],[-85.624,42.864],[-85.624,42.864],[-85.624,42.864],[-85.624,42.864],[-85.624,42.864],[-85.624,42.864],[-85.624,42.865],[-85.624,42.865],[-85.624,42.865],[-85.624,42.865],[-85.624,42.865],[-85.624,42.865],[-85.624,42.865],[-85.624,42.865],[-85.625,42.865],[-85.625,42.865],[-85.625,42.865],[-85.625,42.865],[-85.625,42.865],[-85.625,42.865],[-85.625,42.865],[-85.625,42.865],[-85.625,42.865],[-85.625,42.865],[-85.625,42.865],[-85.625,42.865],[-85.625,42.865],[-85.625,42.865],[-85.626,42.865],[-85.626,42.865],[-85.626,42.864],[-85.626,42.864],[-85.627,42.864],[-85.627,42.864],[-85.627,42.864],[-85.627,42.864],[-85.627,42.864],[-85.627,42.864],[-85.627,42.864],[-85.627,42.864],[-85.627,42.864],[-85.627,42.864],[-85.627,42.864],[-85.627,42.864],[-85.627,42.864],[-85.627,42.864],[-85.627,42.864],[-85.627,42.863],[-85.627,42.863],[-85.627,42.863],[-85.627,42.863],[-85.627,42.863],[-85.627,42.863],[-85.627,42.863],[-85.627,42.863],[-85.627,42.863],[-85.627,42.863],[-85.627,42.863],[-85.627,42.863],[-85.627,42.863],[-85.627,42.863],[-85.627,42.863],[-85.627,42.863],[-85.627,42.862],[-85.626,42.862],[-85.626,42.862],[-85.626,42.862],[-85.626,42.862],[-85.625,42.862],[-85.625,42.862],[-85.625,42.862],[-85.625,42.862],[-85.625,42.862],[-85.625,42.862],[-85.625,42.862]]]},"properties":{"OBJECTID":1004146,"JOB_ID":"68cc7a4795eafa4668c64bee","CUSTOMER_COUNT":12,"CREW_ASSIGNED":1,"GROUP_LEVEL":0,"NEEDS_UPDATED":0,"EST_TIME_RESTORATION":1758248100000,"CAUSE_CD":"5fa41397b71bb212402bcdf7","CAUSE_DESC":"Other","OUTAGE_TIME":1758230497000,"HEADQUARTER":"GRE","SHAPE.STArea()":80084.87840020009,"SHAPE.STLength()":1019.2084685636996}},{"type":"Feature","id":1004147,"geometry":{"type":"Polygon","coordinates":[[[-84.014,43.522],[-84.014,43.522],[-84.013,43.522],[-84.013,43.522],[-84.013,43.522],[-84.013,43.523],[-84.012,43.523],[-84.012,43.523],[-84.012,43.523],[-84.012,43.524],[-84.012,43.524],[-84.012,43.524],[-84.013,43.524],[-84.013,43.525],[-84.013,43.525],[-84.014,43.525],[-84.014,43.525],[-84.014,43.525],[-84.015,43.525],[-84.015,43.525],[-84.015,43.524],[-84.016,43.524],[-84.016,43.524],[-84.016,43.524],[-84.016,43.523],[-84.016,43.523],[-84.016,43.523],[-84.016,43.523],[-84.015,43.522],[-84.015,43.522],[-84.015,43.522],[-84.014,43.522],[-84.014,43.522]]]},"properties":{"OBJECTID":1004147,"JOB_ID":"68cc7b7a95eafa4668c6592e","CUSTOMER_COUNT":1,"CREW_ASSIGNED":1,"GROUP_LEVEL":0,"NEEDS_UPDATED":0,"EST_TIME_RESTORATION":1758248100000,"CAUSE_CD":null,"CAUSE_DESC":null,"OUTAGE_TIME":1758231417000,"HEADQUARTER":"SAG","SHAPE.STArea()":70232.511844384833,"SHAPE.STLength()":940.96451982295082}},{"type":"Feature","id":1004148,"geometry":{"type":"Polygon","coordinates":[[[-84.438,44.002],[-84.447,44.002],[-84.455,44.002],[-84.462,44.002],[-84.464,44.001],[-84.455,44.001],[-84.442,44.001],[-84.438,44.002]]]},"properties":{"OBJECTID":1004148,"JOB_ID":"68cc7c0995eafa4668c65ad8","CUSTOMER_COUNT":16,"CREW_ASSIGNED":0,"GROUP_LEVEL":0,"NEEDS_UPDATED":0,"EST_TIME_RESTORATION":1758255300000,"CAUSE_CD":null,"CAUSE_DESC":null,"OUTAGE_TIME":1758231345000,"HEADQUARTER":"CLR","SHAPE.STArea()":233982.75556002583,"SHAPE.STLength()":4211.4049076168512}},{"type":"Feature","id":1004151,"geometry":{"type":"Polygon","coordinates":[[[-83.716,43.026],[-83.716,43.026],[-83.716,43.026],[-83.715,43.027],[-83.715,43.027],[-83.715,43.027],[-83.715,43.027],[-83.714,43.027],[-83.714,43.028],[-83.714,43.028],[-83.714,43.028],[-83.715,43.028],[-83.715,43.029],[-83.715,43.029],[-83.715,43.029],[-83.716,43.029],[-83.716,43.029],[-83.717,43.029],[-83.717,43.029],[-83.717,43.029],[-83.717,43.029],[-83.718,43.029],[-83.718,43.028],[-83.718,43.028],[-83.718,43.028],[-83.718,43.028],[-83.718,43.027],[-83.718,43.027],[-83.718,43.027],[-83.717,43.027],[-83.717,43.026],[-83.717,43.026],[-83.716,43.026]]]},"properties":{"OBJECTID":1004151,"JOB_ID":"68cc7ddf95eafa4668c67044","CUSTOMER_COUNT":1,"CREW_ASSIGNED":0,"GROUP_LEVEL":0,"NEEDS_UPDATED":0,"EST_TIME_RESTORATION":null,"CAUSE_CD":"5fa41397b71bb212402bcdf8","CAUSE_DESC":"Other","OUTAGE_TIME":1758232027000,"HEADQUARTER":"FLT","SHAPE.STArea()":70232.51431126229,"SHAPE.STLength()":940.9645363484218}},{"type":"Feature","id":1004155,"geometry":{"type":"Polygon","coordinates":[[[-83.803,43.55],[-83.803,43.55],[-83.802,43.55],[-83.802,43.55],[-83.802,43.55],[-83.801,43.55],[-83.801,43.55],[-83.801,43.551],[-83.801,43.551],[-83.801,43.551],[-83.801,43.551],[-83.801,43.552],[-83.802,43.552],[-83.802,43.552],[-83.802,43.552],[-83.803,43.552],[-83.803,43.552],[-83.803,43.552],[-83.804,43.552],[-83.804,43.552],[-83.804,43.552],[-83.804,43.552],[-83.805,43.551],[-83.805,43.551],[-83.805,43.551],[-83.805,43.551],[-83.805,43.55],[-83.805,43.55],[-83.804,43.55],[-83.804,43.55],[-83.804,43.55],[-83.803,43.55],[-83.803,43.55]]]},"properties":{"OBJECTID":1004155,"JOB_ID":"68cc815295eafa4668c679a6","CUSTOMER_COUNT":1,"CREW_ASSIGNED":0,"GROUP_LEVEL":0,"NEEDS_UPDATED":0,"EST_TIME_RESTORATION":null,"CAUSE_CD":null,"CAUSE_DESC":null,"OUTAGE_TIME":1758232913000,"HEADQUARTER":"BCY","SHAPE.STArea()":70232.518419456086,"SHAPE.STLength()":940.96456386912621}}]}